odoo/addons/purchase_default_terms_conditions/README.rst
odoo/addons/purchase_default_terms_conditions/__init__.py
odoo/addons/purchase_default_terms_conditions/__manifest__.py
odoo/addons/purchase_default_terms_conditions/i18n/es.po
odoo/addons/purchase_default_terms_conditions/i18n/it.po
odoo/addons/purchase_default_terms_conditions/i18n/pt_BR.po
odoo/addons/purchase_default_terms_conditions/i18n/purchase_default_terms_conditions.pot
odoo/addons/purchase_default_terms_conditions/models/__init__.py
odoo/addons/purchase_default_terms_conditions/models/purchase.py
odoo/addons/purchase_default_terms_conditions/models/res_company.py
odoo/addons/purchase_default_terms_conditions/models/res_config_settings.py
odoo/addons/purchase_default_terms_conditions/models/res_partner.py
odoo/addons/purchase_default_terms_conditions/readme/CONFIGURE.md
odoo/addons/purchase_default_terms_conditions/readme/CONTRIBUTORS.md
odoo/addons/purchase_default_terms_conditions/readme/CREDITS.md
odoo/addons/purchase_default_terms_conditions/readme/DESCRIPTION.md
odoo/addons/purchase_default_terms_conditions/readme/USAGE.md
odoo/addons/purchase_default_terms_conditions/static/index.html
odoo/addons/purchase_default_terms_conditions/static/description/banner.png
odoo/addons/purchase_default_terms_conditions/static/description/icon.png
odoo/addons/purchase_default_terms_conditions/static/description/index.html
odoo/addons/purchase_default_terms_conditions/tests/__init__.py
odoo/addons/purchase_default_terms_conditions/tests/test_purchase_order.py
odoo/addons/purchase_default_terms_conditions/views/res_config_settings.xml
odoo/addons/purchase_default_terms_conditions/views/res_partner_views.xml
odoo_addon_purchase_default_terms_conditions-18.0.1.0.0.4.dist-info/METADATA
odoo_addon_purchase_default_terms_conditions-18.0.1.0.0.4.dist-info/WHEEL
odoo_addon_purchase_default_terms_conditions-18.0.1.0.0.4.dist-info/top_level.txt
odoo_addon_purchase_default_terms_conditions-18.0.1.0.0.4.dist-info/RECORD
